validator/__init__.py
validator/exception.py
validator/validator.py
validator/decorators/__init__.py
validator/decorators/decorators.py
schema_validator_halpa-0.0.7.dist-info/LICENSE
schema_validator_halpa-0.0.7.dist-info/METADATA
schema_validator_halpa-0.0.7.dist-info/WHEEL
schema_validator_halpa-0.0.7.dist-info/top_level.txt
schema_validator_halpa-0.0.7.dist-info/RECORD
