Metadata-Version: 2.1
Name: schema-validator-halpa
Version: 0.0.7
Summary: A utility to validate JSON schemas with jsonschema with simplejson
Home-page: https://gitlab.com/Halpa/schema-validator-halpa
Author: Halpa AB
Author-email: dev@halpa.se
License: UNKNOWN
Platform: UNKNOWN
Classifier: Programming Language :: Python :: 3
Classifier: Operating System :: OS Independent
Requires-Python: >=3.6
Requires-Dist: simplejson (>=3.17.0)
Requires-Dist: jsonschema (>=3.2.0)
